qiskit_pqcee_provider/VERSION.txt
qiskit_pqcee_provider/__init__.py
qiskit_pqcee_provider/amoy_testnet_config.ini
qiskit_pqcee_provider/backend.py
qiskit_pqcee_provider/job.py
qiskit_pqcee_provider/provider.py
qiskit_pqcee_provider/setup_amoy_testnet.py
qiskit_pqcee_provider/setup_mumbai_testnet.py
qiskit_pqcee_provider/test_provider.py
qiskit_pqcee_provider/contracts/QuantumBackendContract.sol
qiskit_pqcee_provider/contracts/QuantumBackendInterface.sol
qiskit_pqcee_provider/contracts/QuantumProviderContract.sol
qiskit_pqcee_provider/contracts/QuantumProviderInterface.sol
qiskit_pqcee_provider/quic/__init__.py
qiskit_pqcee_provider/quic/backend.py
qiskit_pqcee_provider/quic/gate.py
qiskit_pqcee_provider/quic/target.py
qiskit_pqcee_provider-0.1.5.dist-info/LICENSE.txt
qiskit_pqcee_provider-0.1.5.dist-info/METADATA
qiskit_pqcee_provider-0.1.5.dist-info/WHEEL
qiskit_pqcee_provider-0.1.5.dist-info/top_level.txt
qiskit_pqcee_provider-0.1.5.dist-info/RECORD
