Metadata-Version: 2.1
Name: qiskit-pqcee-provider
Version: 0.1.5
Summary: An 8-qubit universal quantum emulator adapted for web3 platforms, originally presented at IEEE QCE 20. This package takes Qiskit code and converts it to QuICScript, a language developed by pQCee to write quantum circuits.
Home-page: https://github.com/pqcee/qiskit-pqcee-provider
Author: pQCee Product Team
Author-email: info@pqcee.com
License: MIT
Platform: UNKNOWN
Classifier: Intended Audience :: Developers
Classifier: Intended Audience :: Science/Research
Classifier: License :: OSI Approved :: MIT License
Classifier: Operating System :: Microsoft :: Windows
Classifier: Operating System :: MacOS
Classifier: Operating System :: POSIX :: Linux
Classifier: Programming Language :: Python :: 3.10
Classifier: Programming Language :: Python :: 3.11
Classifier: Topic :: Scientific/Engineering
Requires-Python: >=3.10, <4
License-File: LICENSE.txt
Requires-Dist: numpy
Requires-Dist: py-solc-x
Requires-Dist: qiskit-aer
Requires-Dist: qiskit[visualization]
Requires-Dist: scikit-learn
Requires-Dist: web3[tester]
